jsCalc/app.py
jsCalc_0.0.1-0.0.1.dist-info/LICENSE
jsCalc_0.0.1-0.0.1.dist-info/METADATA
jsCalc_0.0.1-0.0.1.dist-info/WHEEL
jsCalc_0.0.1-0.0.1.dist-info/top_level.txt
jsCalc_0.0.1-0.0.1.dist-info/RECORD
